LICENSE
MANIFEST.in
README.md
requirements.txt
setup.py
joker.egg-info/PKG-INFO
joker.egg-info/SOURCES.txt
joker.egg-info/dependency_links.txt
joker.egg-info/namespace_packages.txt
joker.egg-info/not-zip-safe
joker.egg-info/requires.txt
joker.egg-info/top_level.txt
joker/environ/__init__.py
joker/meta/__init__.py
joker/meta/environ.py
joker/meta/utils.py